nxp/__init__.py
nxp/charset.py
nxp/error.py
nxp/helper.py
nxp/logging.py
nxp/ruledef.py
nxp/util.py
nxp/expr/__init__.py
nxp/expr/alias.py
nxp/expr/base.py
nxp/expr/compose.py
nxp/expr/content.py
nxp/expr/match.py
nxp/expr/operation.py
nxp/expr/repeat.py
nxp/expr/util.py
nxp/io/__init__.py
nxp/io/buffer.py
nxp/io/cursor.py
nxp/io/line.py
nxp/io/transform.py
nxp/io/util.py
nxp/parse/__init__.py
nxp/parse/context.py
nxp/parse/event.py
nxp/parse/match.py
nxp/parse/parser.py
nxp/parse/rule.py
nxp/parse/util.py
nxp-0.3.1.dist-info/LICENSE.txt
nxp-0.3.1.dist-info/METADATA
nxp-0.3.1.dist-info/WHEEL
nxp-0.3.1.dist-info/top_level.txt
nxp-0.3.1.dist-info/RECORD
