Metadata-Version: 2.1
Name: nxp
Version: 0.3.1
Summary: Natural eXpression Parsing — A Python 3 parsing library.
Home-page: https://github.com/jhadida/nxp
Author: Jonathan Hadida
Author-email: jonathan.hadida@unknown.invalid
License: UNKNOWN
Platform: UNKNOWN
Classifier: Development Status :: 3 - Alpha
Classifier: Intended Audience :: Developers
Classifier: Programming Language :: Python :: 3
Classifier: Topic :: Text Processing
Classifier: License :: OSI Approved :: European Union Public Licence 1.2 (EUPL 1.2)
Classifier: Operating System :: OS Independent
Requires-Python: >=3.6
